vericold_plotter/__init__.py
vericold_plotter/__main__.py
vericold_plotter/_version.py
vericold_plotter/log_parser.py
vericold_plotter/gui/__init__.py
vericold_plotter/gui/_data_model.py
vericold_plotter/gui/_file_dialog.py
vericold_plotter/gui/_menu_bar.py
vericold_plotter/gui/_open_file_path_entry.py
vericold_plotter/gui/_plot.py
vericold_plotter/gui/_plot_line_options.py
vericold_plotter/gui/_preferences.py
vericold_plotter/gui/_settings.py
vericold_plotter/gui/_time_span_edit.py
vericold_plotter/gui/_ui.py
vericold_plotter-1.0.0.dist-info/METADATA
vericold_plotter-1.0.0.dist-info/WHEEL
vericold_plotter-1.0.0.dist-info/entry_points.txt
vericold_plotter-1.0.0.dist-info/top_level.txt
vericold_plotter-1.0.0.dist-info/RECORD
